[{"id":18,"annotations":[{"id":3,"completed_by":1,"result":[{"value":{"start":0,"end":8,"text":"ENHANCIN","labels":["B-MEDICATION_NAME"]},"id":"C9k0UTTARA","from_name":"label","to_name":"text","type":"labels","origin":"manual"},{"value":{"start":9,"end":14,"text":"625MG","labels":["O"]},"id":"iSHMxv3ds4","from_name":"label","to_name":"text","type":"labels","origin":"manual"},{"value":{"start":16,"end":25,"text":"AUGMENTIN","labels":["B-MEDICATION_NAME"]},"id":"xwjuqEAiwR","from_name":"label","to_name":"text","type":"labels","origin":"manual"},{"value":{"start":31,"end":53,"text":"Qty 10.00 tab s Take","labels":["O"]},"id":"XQltd_Slw_","from_name":"label","to_name":"text","type":"labels","origin":"manual"},{"value":{"start":54,"end":55,"text":"1","labels":["B-DOSAGE"]},"id":"eVH1fC9hMB","from_name":"label","to_name":"text","type":"labels","origin":"manual"},{"value":{"start":56,"end":59,"text":"tab","labels":["I-DOSAGE"]},"id":"kFEHlkTQVM","from_name":"label","to_name":"text","type":"labels","origin":"manual"},{"value":{"start":62,"end":63,"text":"2","labels":["B-FREQUENCY"]},"id":"C_xjja1HfM","from_name":"label","to_name":"text","type":"labels","origin":"manual"},{"value":{"start":64,"end":69,"text":"times","labels":["I-FREQUENCY"]},"id":"xLJSaYnF4d","from_name":"label","to_name":"text","type":"labels","origin":"manual"},{"value":{"start":70,"end":75,"text":"a day","labels":["B-FREQUENCY"]},"id":"0cVnLWLHfx","from_name":"label","to_name":"text","type":"labels","origin":"manual"},{"value":{"start":76,"end":80,"text":"Take","labels":["B-INSTRUCTION"]},"id":"J8_jQSu3al","from_name":"label","to_name":"text","type":"labels","origin":"manual"},{"value":{"start":81,"end":91,"text":"after food","labels":["I-INSTRUCTION"]},"id":"YPgFr-TkqZ","from_name":"label","to_name":"text","type":"labels","origin":"manual"},{"value":{"start":98,"end":106,"text":"complete","labels":["O"]},"id":"MvtfOpWfME","from_name":"label","to_name":"text","type":"labels","origin":"manual"},{"value":{"start":107,"end":128,"text":"course of Antibiotics","labels":["I-NOTE"]},"id":"qw4qJNpL9n","from_name":"label","to_name":"text","type":"labels","origin":"manual"},{"value":{"start":60,"end":61,"text":"s","labels":["O"]},"id":"lPgw7NfRHR","from_name":"label","to_name":"text","type":"labels","origin":"manual"},{"value":{"start":95,"end":97,"text":"To","labels":["O"]},"id":"Bh5ySNq4Kp","from_name":"label","to_name":"text","type":"labels","origin":"manual"}],"was_cancelled":false,"ground_truth":false,"created_at":"2025-08-02T08:44:50.714420Z","updated_at":"2025-08-02T08:45:08.082754Z","draft_created_at":"2025-08-02T08:43:11.284563Z","lead_time":133.234,"prediction":{},"result_count":15,"unique_id":"5a18e47c-63c3-4439-820a-aee8b9371858","import_id":null,"last_action":null,"bulk_created":false,"task":18,"project":3,"updated_by":1,"parent_prediction":null,"parent_annotation":null,"last_created_by":null}],"file_upload":"0ccc64d3-label_studio_tasks_1.json","drafts":[],"predictions":[],"data":{"text":"ENHANCIN 625MG  AUGMENTIN      Qty   10.00 tab s Take 1 tab s 2 times a day Take after food    To complete course of Antibiotics"},"meta":{},"created_at":"2025-08-02T08:41:52.916251Z","updated_at":"2025-08-02T08:45:08.133606Z","inner_id":1,"total_annotations":1,"cancelled_annotations":0,"total_predictions":0,"comment_count":0,"unresolved_comment_count":0,"last_comment_updated_at":null,"project":3,"updated_by":1,"comment_authors":[]},{"id":19,"annotations":[{"id":4,"completed_by":1,"result":[{"value":{"start":0,"end":11,"text":"MONTELUKAST","labels":["B-MEDICATION_NAME"]},"id":"42mkXmI6rO","from_name":"label","to_name":"text","type":"labels","origin":"manual"},{"value":{"start":42,"end":43,"text":"1","labels":["B-FREQUENCY"]},"id":"4RA8L7PAFu","from_name":"label","to_name":"text","type":"labels","origin":"manual"},{"value":{"start":44,"end":47,"text":"tab","labels":["I-FREQUENCY"]},"id":"JZk42hLlXx","from_name":"label","to_name":"text","type":"labels","origin":"manual"},{"value":{"start":50,"end":55,"text":"Every","labels":["B-FREQUENCY"]},"id":"IcBv7M1Xcn","from_name":"label","to_name":"text","type":"labels","origin":"manual"},{"value":{"start":56,"end":61,"text":"night","labels":["I-FREQUENCY"]},"id":"orOQ2768Y7","from_name":"label","to_name":"text","type":"labels","origin":"manual"},{"value":{"start":77,"end":81,"text":"Take","labels":["B-INSTRUCTION"]},"id":"Ywk2N4B9vv","from_name":"label","to_name":"text","type":"labels","origin":"manual"},{"value":{"start":82,"end":92,"text":"after food","labels":["I-INSTRUCTION"]},"id":"zSmeqy85Ey","from_name":"label","to_name":"text","type":"labels","origin":"manual"},{"value":{"start":62,"end":66,"text":"OPEN","labels":["B-NOTE"]},"id":"zCJHRZw6aw","from_name":"label","to_name":"text","type":"labels","origin":"manual"},{"value":{"start":67,"end":73,"text":"AIRWAY","labels":["I-NOTE"]},"id":"lhr198ezen","from_name":"label","to_name":"text","type":"labels","origin":"manual"},{"value":{"start":12,"end":41,"text":"10MG Qty 10.00tab s Take","labels":["O"]},"id":"meLVR5RX2g","from_name":"label","to_name":"text","type":"labels","origin":"manual"},{"value":{"start":48,"end":49,"text":"s","labels":["O"]},"id":"AgMCY9Ol5X","from_name":"label","to_name":"text","type":"labels","origin":"manual"}],"was_cancelled":false,"ground_truth":false,"created_at":"2025-08-02T08:48:35.981260Z","updated_at":"2025-08-02T08:48:35.981260Z","draft_created_at":"2025-08-02T08:45:21.578424Z","lead_time":205.402,"prediction":{},"result_count":11,"unique_id":"b268d8e8-23fa-4288-a776-505c349e3eac","import_id":null,"last_action":null,"bulk_created":false,"task":19,"project":3,"updated_by":1,"parent_prediction":null,"parent_annotation":null,"last_created_by":null}],"file_upload":"0ccc64d3-label_studio_tasks_1.json","drafts":[],"predictions":[],"data":{"text":"MONTELUKAST 10MG    Qty   10.00tab s Take 1 tab s Every night OPEN AIRWAY    Take after food"},"meta":{},"created_at":"2025-08-02T08:41:52.916251Z","updated_at":"2025-08-02T08:48:36.009802Z","inner_id":2,"total_annotations":1,"cancelled_annotations":0,"total_predictions":0,"comment_count":0,"unresolved_comment_count":0,"last_comment_updated_at":null,"project":3,"updated_by":1,"comment_authors":[]},{"id":20,"annotations":[{"id":5,"completed_by":1,"result":[{"value":{"start":0,"end":11,"text":"Prenisolone","labels":["B-MEDICATION_NAME"]},"id":"K74YbDcy4C","from_name":"label","to_name":"text","type":"labels","origin":"manual"},{"value":{"start":12,"end":36,"text":"5 mg Qty 12.00 tab s","labels":["O"]},"id":"HmSelX9uRG","from_name":"label","to_name":"text","type":"labels","origin":"manual"},{"value":{"start":37,"end":41,"text":"Take","labels":["O"]},"id":"sMpOnUNlQb","from_name":"label","to_name":"text","type":"labels","origin":"manual"},{"value":{"start":42,"end":43,"text":"1","labels":["B-DOSAGE"]},"id":"0nwWz1GNpU","from_name":"label","to_name":"text","type":"labels","origin":"manual"},{"value":{"start":44,"end":47,"text":"tab","labels":["I-DOSAGE"]},"id":"VUkMbLXIDJ","from_name":"label","to_name":"text","type":"labels","origin":"manual"},{"value":{"start":48,"end":49,"text":"s","labels":["O"]},"id":"XdvUtWSEpP","from_name":"label","to_name":"text","type":"labels","origin":"manual"},{"value":{"start":50,"end":55,"text":"Every","labels":["B-FREQUENCY"]},"id":"nxQ2sOyMb9","from_name":"label","to_name":"text","type":"labels","origin":"manual"},{"value":{"start":56,"end":63,"text":"morning","labels":["I-FREQUENCY"]},"id":"L9P92zbrc9","from_name":"label","to_name":"text","type":"labels","origin":"manual"},{"value":{"start":64,"end":68,"text":"Take","labels":["B-INSTRUCTION"]},"id":"zFTR1OQWbh","from_name":"label","to_name":"text","type":"labels","origin":"manual"},{"value":{"start":69,"end":79,"text":"after food","labels":["I-INSTRUCTION"]},"id":"HSJ-a_iXOP","from_name":"label","to_name":"text","type":"labels","origin":"manual"}],"was_cancelled":false,"ground_truth":false,"created_at":"2025-08-02T08:49:43.974049Z","updated_at":"2025-08-02T08:49:43.974049Z","draft_created_at":"2025-08-02T08:48:52.248446Z","lead_time":66.554,"prediction":{},"result_count":10,"unique_id":"8be12610-affd-4c29-9ea1-7023ec6419c3","import_id":null,"last_action":null,"bulk_created":false,"task":20,"project":3,"updated_by":1,"parent_prediction":null,"parent_annotation":null,"last_created_by":null}],"file_upload":"0ccc64d3-label_studio_tasks_1.json","drafts":[],"predictions":[],"data":{"text":"Prenisolone 5 mg    Qty  12.00 tab s Take 1 tab s Every morning Take after food"},"meta":{},"created_at":"2025-08-02T08:41:52.916251Z","updated_at":"2025-08-02T08:49:44.004837Z","inner_id":3,"total_annotations":1,"cancelled_annotations":0,"total_predictions":0,"comment_count":0,"unresolved_comment_count":0,"last_comment_updated_at":null,"project":3,"updated_by":1,"comment_authors":[]},{"id":21,"annotations":[{"id":6,"completed_by":1,"result":[{"value":{"start":0,"end":7,"text":"Telfast","labels":["B-MEDICATION_NAME"]},"id":"xARvqNYYaX","from_name":"label","to_name":"text","type":"labels","origin":"manual"},{"value":{"start":40,"end":41,"text":"1","labels":["B-DOSAGE"]},"id":"l33k-5D5nj","from_name":"label","to_name":"text","type":"labels","origin":"manual"},{"value":{"start":42,"end":45,"text":"tab","labels":["I-DOSAGE"]},"id":"iimsPykg8F","from_name":"label","to_name":"text","type":"labels","origin":"manual"},{"value":{"start":48,"end":49,"text":"1","labels":["B-FREQUENCY"]},"id":"0u8qfyCsRo","from_name":"label","to_name":"text","type":"labels","origin":"manual"},{"value":{"start":50,"end":54,"text":"time","labels":["I-FREQUENCY"]},"id":"MAmgFoYphB","from_name":"label","to_name":"text","type":"labels","origin":"manual"},{"value":{"start":65,"end":69,"text":"NOSE","labels":["B-NOTE"]},"id":"BQLQ-KWtWL","from_name":"label","to_name":"text","type":"labels","origin":"manual"},{"value":{"start":86,"end":90,"text":"Take","labels":["B-INSTRUCTION"]},"id":"SiGZLOAnUA","from_name":"label","to_name":"text","type":"labels","origin":"manual"},{"value":{"start":91,"end":101,"text":"after food","labels":["I-INSTRUCTION"]},"id":"q5RYZyCcl5","from_name":"label","to_name":"text","type":"labels","origin":"manual"},{"value":{"start":8,"end":39,"text":"180 mg Qty 10.00 tab s Take","labels":["O"]},"id":"8Vp-RX3sI_","from_name":"label","to_name":"text","type":"labels","origin":"manual"},{"value":{"start":46,"end":47,"text":"s","labels":["O"]},"id":"YdChU2xgeE","from_name":"label","to_name":"text","type":"labels","origin":"manual"},{"value":{"start":55,"end":64,"text":"a day For","labels":["O"]},"id":"d0XmUTfrDh","from_name":"label","to_name":"text","type":"labels","origin":"manual"},{"value":{"start":70,"end":82,"text":"ALLERGY ITCH","labels":["I-NOTE"]},"id":"Kq4i9_yVY4","from_name":"label","to_name":"text","type":"labels","origin":"manual"}],"was_cancelled":false,"ground_truth":false,"created_at":"2025-08-02T08:51:50.807569Z","updated_at":"2025-08-02T08:51:50.807569Z","draft_created_at":"2025-08-02T08:49:57.369339Z","lead_time":125.739,"prediction":{},"result_count":12,"unique_id":"e3172003-7a48-4573-8cc3-01a15f84a88d","import_id":null,"last_action":null,"bulk_created":false,"task":21,"project":3,"updated_by":1,"parent_prediction":null,"parent_annotation":null,"last_created_by":null}],"file_upload":"0ccc64d3-label_studio_tasks_1.json","drafts":[],"predictions":[],"data":{"text":"Telfast 180 mg   Qty   10.00 tab s Take 1 tab s 1 time a day For NOSE ALLERGY ITCH    Take after food"},"meta":{},"created_at":"2025-08-02T08:41:52.916251Z","updated_at":"2025-08-02T08:51:50.834391Z","inner_id":4,"total_annotations":1,"cancelled_annotations":0,"total_predictions":0,"comment_count":0,"unresolved_comment_count":0,"last_comment_updated_at":null,"project":3,"updated_by":1,"comment_authors":[]},{"id":22,"annotations":[{"id":7,"completed_by":1,"result":[{"value":{"start":0,"end":8,"text":"Celebrex","labels":["B-MEDICATION_NAME"]},"id":"6L9w_xS7QX","from_name":"label","to_name":"text","type":"labels","origin":"manual"},{"value":{"start":43,"end":44,"text":"1","labels":["B-DOSAGE"]},"id":"mNnaZ-W6JV","from_name":"label","to_name":"text","type":"labels","origin":"manual"},{"value":{"start":45,"end":48,"text":"cap","labels":["I-DOSAGE"]},"id":"u4tJCVlWPW","from_name":"label","to_name":"text","type":"labels","origin":"manual"},{"value":{"start":51,"end":52,"text":"2","labels":["B-FREQUENCY"]},"id":"Xk_T3F8AKb","from_name":"label","to_name":"text","type":"labels","origin":"manual"},{"value":{"start":53,"end":58,"text":"times","labels":["I-FREQUENCY"]},"id":"kjS41jMvWy","from_name":"label","to_name":"text","type":"labels","origin":"manual"},{"value":{"start":65,"end":75,"text":"Painkiller","labels":["B-NOTE"]},"id":"NWvKeJNUvo","from_name":"label","to_name":"text","type":"labels","origin":"manual"},{"value":{"start":76,"end":80,"text":"Anti","labels":["B-NOTE"]},"id":"q__nLqXDRe","from_name":"label","to_name":"text","type":"labels","origin":"manual"},{"value":{"start":82,"end":94,"text":"inflammation","labels":["I-NOTE"]},"id":"M1h77EuyyL","from_name":"label","to_name":"text","type":"labels","origin":"manual"},{"value":{"start":97,"end":101,"text":"Take","labels":["B-INSTRUCTION"]},"id":"ozuKMSMDot","from_name":"label","to_name":"text","type":"labels","origin":"manual"},{"value":{"start":102,"end":112,"text":"after food","labels":["I-INSTRUCTION"]},"id":"fUYonxP1lP","from_name":"label","to_name":"text","type":"labels","origin":"manual"},{"value":{"start":9,"end":42,"text":"cap 200mg Qty 10.00 cap s Take","labels":["O"]},"id":"vxagoKa5qo","from_name":"label","to_name":"text","type":"labels","origin":"manual"},{"value":{"start":59,"end":64,"text":"a day","labels":["O"]},"id":"XxpWOLQ4ED","from_name":"label","to_name":"text","type":"labels","origin":"manual"}],"was_cancelled":false,"ground_truth":false,"created_at":"2025-08-02T08:52:56.308447Z","updated_at":"2025-08-02T08:52:56.308447Z","draft_created_at":"2025-08-02T08:52:01.355777Z","lead_time":64.424,"prediction":{},"result_count":12,"unique_id":"9344d3d6-be5a-4abe-9a88-8c274ca90ca9","import_id":null,"last_action":null,"bulk_created":false,"task":22,"project":3,"updated_by":1,"parent_prediction":null,"parent_annotation":null,"last_created_by":null}],"file_upload":"0ccc64d3-label_studio_tasks_1.json","drafts":[],"predictions":[],"data":{"text":"Celebrex cap 200mg    Qty 10.00 cap s Take 1 cap s 2 times a day Painkiller Anti  inflammation   Take after food"},"meta":{},"created_at":"2025-08-02T08:41:52.916251Z","updated_at":"2025-08-02T08:52:56.341986Z","inner_id":5,"total_annotations":1,"cancelled_annotations":0,"total_predictions":0,"comment_count":0,"unresolved_comment_count":0,"last_comment_updated_at":null,"project":3,"updated_by":1,"comment_authors":[]},{"id":23,"annotations":[{"id":8,"completed_by":1,"result":[{"value":{"start":4,"end":12,"text":"Lozenges","labels":["B-MEDICATION_NAME"]},"id":"X4I4vQXd7V","from_name":"label","to_name":"text","type":"labels","origin":"manual"},{"value":{"start":38,"end":39,"text":"1","labels":["B-DOSAGE"]},"id":"XtLtM-1WIq","from_name":"label","to_name":"text","type":"labels","origin":"manual"},{"value":{"start":40,"end":43,"text":"tab","labels":["I-DOSAGE"]},"id":"qXqkgSd_Vu","from_name":"label","to_name":"text","type":"labels","origin":"manual"},{"value":{"start":46,"end":47,"text":"3","labels":["B-FREQUENCY"]},"id":"i3vHu0smEu","from_name":"label","to_name":"text","type":"labels","origin":"manual"},{"value":{"start":48,"end":53,"text":"times","labels":["I-FREQUENCY"]},"id":"5xfYqXB5mv","from_name":"label","to_name":"text","type":"labels","origin":"manual"},{"value":{"start":60,"end":64,"text":"Take","labels":["B-INSTRUCTION"]},"id":"RIHXSsevVC","from_name":"label","to_name":"text","type":"labels","origin":"manual"},{"value":{"start":65,"end":78,"text":"as Instructed","labels":["I-INSTRUCTION"]},"id":"5y_oPpNYhB","from_name":"label","to_name":"text","type":"labels","origin":"manual"},{"value":{"start":0,"end":3,"text":"Mac","labels":["O"]},"id":"rQbR8iXKm6","from_name":"label","to_name":"text","type":"labels","origin":"manual"},{"value":{"start":16,"end":37,"text":"Qty 24.00 tab s Suck","labels":["O"]},"id":"PS9dg6645h","from_name":"label","to_name":"text","type":"labels","origin":"manual"},{"value":{"start":44,"end":45,"text":"s","labels":["O"]},"id":"aT6mQ3zC6t","from_name":"label","to_name":"text","type":"labels","origin":"manual"},{"value":{"start":54,"end":59,"text":"a day","labels":["O"]},"id":"JOfIq_mzQ4","from_name":"label","to_name":"text","type":"labels","origin":"manual"}],"was_cancelled":false,"ground_truth":false,"created_at":"2025-08-02T08:54:44.685428Z","updated_at":"2025-08-02T08:54:44.685428Z","draft_created_at":"2025-08-02T08:53:20.500643Z","lead_time":105.006,"prediction":{},"result_count":11,"unique_id":"505a6a73-accc-455f-95d6-142cb2c5a1ed","import_id":null,"last_action":null,"bulk_created":false,"task":23,"project":3,"updated_by":1,"parent_prediction":null,"parent_annotation":null,"last_created_by":null}],"file_upload":"0ccc64d3-label_studio_tasks_1.json","drafts":[],"predictions":[],"data":{"text":"Mac Lozenges    Qty  24.00 tab s Suck 1 tab s 3 times a day Take as Instructed"},"meta":{},"created_at":"2025-08-02T08:41:52.917251Z","updated_at":"2025-08-02T08:54:44.715585Z","inner_id":6,"total_annotations":1,"cancelled_annotations":0,"total_predictions":0,"comment_count":0,"unresolved_comment_count":0,"last_comment_updated_at":null,"project":3,"updated_by":1,"comment_authors":[]},{"id":24,"annotations":[{"id":9,"completed_by":1,"result":[{"value":{"start":0,"end":11,"text":"RABEPRAZOLE","labels":["B-MEDICATION_NAME"]},"id":"U4ls0hrWr2","from_name":"label","to_name":"text","type":"labels","origin":"manual"},{"value":{"start":41,"end":42,"text":"1","labels":["B-DOSAGE"]},"id":"6v5O-P3-6r","from_name":"label","to_name":"text","type":"labels","origin":"manual"},{"value":{"start":43,"end":46,"text":"tab","labels":["I-DOSAGE"]},"id":"Kc-ywuBTrD","from_name":"label","to_name":"text","type":"labels","origin":"manual"},{"value":{"start":49,"end":50,"text":"1","labels":["B-FREQUENCY"]},"id":"P7pJwNAqD6","from_name":"label","to_name":"text","type":"labels","origin":"manual"},{"value":{"start":51,"end":55,"text":"time","labels":["I-FREQUENCY"]},"id":"YL2J5TByNc","from_name":"label","to_name":"text","type":"labels","origin":"manual"},{"value":{"start":67,"end":74,"text":"Gastric","labels":["B-NOTE"]},"id":"Go2IDUylv9","from_name":"label","to_name":"text","type":"labels","origin":"manual"},{"value":{"start":78,"end":82,"text":"Take","labels":["B-INSTRUCTION"]},"id":"En2uQVdyrC","from_name":"label","to_name":"text","type":"labels","origin":"manual"},{"value":{"start":83,"end":94,"text":"before food","labels":["I-INSTRUCTION"]},"id":"eHuofDndIF","from_name":"label","to_name":"text","type":"labels","origin":"manual"},{"value":{"start":12,"end":40,"text":"20MG Qty 7.00 tab s Take","labels":["O"]},"id":"31NVGUI1JO","from_name":"label","to_name":"text","type":"labels","origin":"manual"},{"value":{"start":47,"end":48,"text":"s","labels":["O"]},"id":"i7RMe9wRCM","from_name":"label","to_name":"text","type":"labels","origin":"manual"},{"value":{"start":56,"end":66,"text":"a day For","labels":["O"]},"id":"kOgNA2gF1I","from_name":"label","to_name":"text","type":"labels","origin":"manual"}],"was_cancelled":false,"ground_truth":false,"created_at":"2025-08-02T08:58:21.825000Z","updated_at":"2025-08-02T08:58:21.825000Z","draft_created_at":"2025-08-02T08:55:29.667557Z","lead_time":215.818,"prediction":{},"result_count":11,"unique_id":"c9e3cb11-2e58-46f1-89d5-f06ffe76429b","import_id":null,"last_action":null,"bulk_created":false,"task":24,"project":3,"updated_by":1,"parent_prediction":null,"parent_annotation":null,"last_created_by":null}],"file_upload":"0ccc64d3-label_studio_tasks_1.json","drafts":[],"predictions":[],"data":{"text":"RABEPRAZOLE 20MG    Qty  7.00 tab s Take 1 tab s 1 time a day  For Gastric    Take before food"},"meta":{},"created_at":"2025-08-02T08:41:52.917251Z","updated_at":"2025-08-02T08:58:21.851845Z","inner_id":7,"total_annotations":1,"cancelled_annotations":0,"total_predictions":0,"comment_count":0,"unresolved_comment_count":0,"last_comment_updated_at":null,"project":3,"updated_by":1,"comment_authors":[]},{"id":25,"annotations":[{"id":10,"completed_by":1,"result":[{"value":{"start":0,"end":8,"text":"PROGESIC","labels":["B-MEDICATION_NAME"]},"id":"h2Zb-NqZLO","from_name":"label","to_name":"text","type":"labels","origin":"manual"},{"value":{"start":10,"end":21,"text":"Paracetamol","labels":["I-MEDICATION_NAME"]},"id":"xBj8OQ9AFl","from_name":"label","to_name":"text","type":"labels","origin":"manual"},{"value":{"start":43,"end":44,"text":"2","labels":["B-DOSAGE"]},"id":"B_M_8SPNbc","from_name":"label","to_name":"text","type":"labels","origin":"manual"},{"value":{"start":45,"end":48,"text":"TAB","labels":["I-DOSAGE"]},"id":"kSCiT_cYuu","from_name":"label","to_name":"text","type":"labels","origin":"manual"},{"value":{"start":51,"end":52,"text":"3","labels":["B-FREQUENCY"]},"id":"pZ81Y4m9Ix","from_name":"label","to_name":"text","type":"labels","origin":"manual"},{"value":{"start":53,"end":58,"text":"times","labels":["I-FREQUENCY"]},"id":"CV9HpGqFbO","from_name":"label","to_name":"text","type":"labels","origin":"manual"},{"value":{"start":88,"end":92,"text":"WITH","labels":["B-INSTRUCTION"]},"id":"Gum_G139-n","from_name":"label","to_name":"text","type":"labels","origin":"manual"},{"value":{"start":93,"end":108,"text":"OR WITHOUT FOOD","labels":["I-INSTRUCTION"]},"id":"SRmb7bxpdj","from_name":"label","to_name":"text","type":"labels","origin":"manual"},{"value":{"start":139,"end":143,"text":"WHEN","labels":["B-NOTE"]},"id":"89dMaEO_Kz","from_name":"label","to_name":"text","type":"labels","origin":"manual"},{"value":{"start":144,"end":153,"text":"NECESSARY","labels":["I-NOTE"]},"id":"mOzykd3O2R","from_name":"label","to_name":"text","type":"labels","origin":"manual"},{"value":{"start":24,"end":42,"text":"500 mg Tablet Take","labels":["O"]},"id":"lKhEO4kLdT","from_name":"label","to_name":"text","type":"labels","origin":"manual"},{"value":{"start":49,"end":50,"text":"S","labels":["O"]},"id":"Njudqxd2M4","from_name":"label","to_name":"text","type":"labels","origin":"manual"},{"value":{"start":69,"end":74,"text":"fever","labels":["B-NOTE"]},"id":"PpBrh-a62H","from_name":"label","to_name":"text","type":"labels","origin":"manual"},{"value":{"start":76,"end":81,"text":"aches","labels":["I-NOTE"]},"id":"WYvy6R6Ze-","from_name":"label","to_name":"text","type":"labels","origin":"manual"},{"value":{"start":83,"end":87,"text":"pain","labels":["I-NOTE"]},"id":"9ouue24ihj","from_name":"label","to_name":"text","type":"labels","origin":"manual"},{"value":{"start":59,"end":68,"text":"a day for","labels":["O"]},"id":"I_37597Xhq","from_name":"label","to_name":"text","type":"labels","origin":"manual"},{"value":{"start":109,"end":138,"text":"STOP WHEN SYMPTOMS ARE BETTER","labels":["O"]},"id":"eWrZQd76dS","from_name":"label","to_name":"text","type":"labels","origin":"manual"}],"was_cancelled":false,"ground_truth":false,"created_at":"2025-08-02T09:10:43.570694Z","updated_at":"2025-08-02T09:10:43.570694Z","draft_created_at":"2025-08-02T09:01:41.385564Z","lead_time":592.545,"prediction":{},"result_count":17,"unique_id":"adc57c62-46a0-4222-8b6b-e814464f6abb","import_id":null,"last_action":null,"bulk_created":false,"task":25,"project":3,"updated_by":1,"parent_prediction":null,"parent_annotation":null,"last_created_by":null}],"file_upload":"0ccc64d3-label_studio_tasks_1.json","drafts":[],"predictions":[],"data":{"text":"PROGESIC  Paracetamol   500 mg Tablet Take 2 TAB S 3 times a day for fever, aches, pain WITH OR WITHOUT FOOD STOP WHEN SYMPTOMS ARE BETTER WHEN NECESSARY"},"meta":{},"created_at":"2025-08-02T08:41:52.917251Z","updated_at":"2025-08-02T09:10:43.598678Z","inner_id":8,"total_annotations":1,"cancelled_annotations":0,"total_predictions":0,"comment_count":0,"unresolved_comment_count":0,"last_comment_updated_at":null,"project":3,"updated_by":1,"comment_authors":[]}]